gradesucope/__init__.py
gradesucope/gradesucope.py
gradesucope-1.10.0.dist-info/LICENSE
gradesucope-1.10.0.dist-info/METADATA
gradesucope-1.10.0.dist-info/WHEEL
gradesucope-1.10.0.dist-info/top_level.txt
gradesucope-1.10.0.dist-info/RECORD
