Metadata-Version: 2.1
Name: gradesucope
Version: 1.10.0
Summary: Libraries that make it easier to write nice Gradescope autograders at UC.
Home-page: https://github.com/hawkinsw/gradesucope
Author: Will Hawkins
Author-email: whh8b@obs.cr
License: GPLv3
Classifier: License :: OSI Approved :: GNU General Public License v3 (GPLv3)
Classifier: Programming Language :: Python :: 3
License-File: LICENSE
Requires-Dist: gradescope-utils
Requires-Dist: subprocess32
